AUTHORS
ChangeLog
LICENSE
Readme.rst
requirements.txt
setup.cfg
setup.py
tox.ini
collectors/__init__.py
collectors/logger.py
collectors/lvm_collector.py
collectors/main.py
collectors/mongo_collector.py
collectors/sentry_events_collector.py
collectors/sql_collector.py
collectors/utils.py
etc/mongo.yml
etc/sentry.yml
etc/sql.yml
promethor.egg-info/PKG-INFO
promethor.egg-info/SOURCES.txt
promethor.egg-info/dependency_links.txt
promethor.egg-info/entry_points.txt
promethor.egg-info/not-zip-safe
promethor.egg-info/pbr.json
promethor.egg-info/requires.txt
promethor.egg-info/top_level.txt