Metadata-Version: 1.1
Name: promethor
Version: 1.2.1
Summary: This is a bunch of custom prometheus collectors.
Home-page: https://github.com/FromZeus/promethor
Author: Daniil Trishkin
Author-email: asteroid566@gmail.com
License: UNKNOWN
Platform: UNKNOWN
Classifier: Intended Audience :: Information Technology
Classifier: Intended Audience :: System Administrators
Classifier: License :: OSI Approved :: Apache Software License
Classifier: Operating System :: POSIX :: Linux
Classifier: Programming Language :: Python
Classifier: Programming Language :: Python :: 2
Classifier: Programming Language :: Python :: 2.7
